django_dans_notifications/__init__.py
django_dans_notifications/admin.py
django_dans_notifications/apps.py
django_dans_notifications/email_sender.py
django_dans_notifications/helpers.py
django_dans_notifications/logging.py
django_dans_notifications/notification_manager.py
django_dans_notifications/serializers.py
django_dans_notifications/threads.py
django_dans_notifications/urls.py
django_dans_notifications/migrations/0001_initial.py
django_dans_notifications/migrations/0002_alter_notificationemailtemplate_options.py
django_dans_notifications/migrations/__init__.py
django_dans_notifications/models/__init__.py
django_dans_notifications/models/base.py
django_dans_notifications/models/notifications.py
django_dans_notifications/templates/django-dans-emails/base.html
django_dans_notifications/templates/django-dans-emails/contact.html
django_dans_notifications/templates/django-dans-emails/default.html
django_dans_notifications/templates/django-dans-emails/empty.html
django_dans_notifications/templates/django-dans-emails/password_reset_request.html
django_dans_notifications/templates/django-dans-emails/template.html
django_dans_notifications/test/__init__.py
django_dans_notifications/test/settings.py
django_dans_notifications/test/test_email_sender.py
django_dans_notifications/test/test_helpers.py
django_dans_notifications/test/test_notification_manager.py
django_dans_notifications/test/test_threads.py
django_dans_notifications/test/model_tests/__init__.py
django_dans_notifications/test/model_tests/base.py
django_dans_notifications/test/model_tests/basic/__init__.py
django_dans_notifications/test/model_tests/basic/test_notification_basic.py
django_dans_notifications/test/model_tests/email/__init__.py
django_dans_notifications/test/model_tests/email/test_notification_email.py
django_dans_notifications/test/model_tests/email/test_notification_email_manager.py
django_dans_notifications/test/model_tests/email/test_notification_email_template.py
django_dans_notifications-1.3.0.dist-info/licenses/AUTHORS
django_dans_notifications-1.3.0.dist-info/licenses/LICENSE
django_dans_notifications-1.3.0.dist-info/METADATA
django_dans_notifications-1.3.0.dist-info/WHEEL
django_dans_notifications-1.3.0.dist-info/top_level.txt
django_dans_notifications-1.3.0.dist-info/RECORD
